rheed_learn/__init__.py
rheed_learn/skeleton.py
RHEED_Learn-0.1.0.dist-info/LICENSE.txt
RHEED_Learn-0.1.0.dist-info/METADATA
RHEED_Learn-0.1.0.dist-info/WHEEL
RHEED_Learn-0.1.0.dist-info/top_level.txt
RHEED_Learn-0.1.0.dist-info/RECORD
