Metadata-Version: 2.1
Name: RHEED-Learn
Version: 0.1.0
Summary: RHEED-Learn is a Python package for analyzing and visualizing Reflection High-Energy Electron Diffraction (RHEED) data, designed to streamline the processing of thin-film growth data and assist with materials characterization.
Home-page: https://github.com/pyscaffold/pyscaffold/
Author: Yichen Guo
Author-email: yig319@lehigh.edu
License: MIT
Project-URL: Documentation, https://pyscaffold.org/
Platform: any
Classifier: Development Status :: 4 - Beta
Classifier: Programming Language :: Python
License-File: LICENSE.txt
Requires-Dist: importlib-metadata ; python_version < "3.8"
Provides-Extra: testing
Requires-Dist: setuptools ; extra == 'testing'
Requires-Dist: pytest ; extra == 'testing'
Requires-Dist: pytest-cov ; extra == 'testing'
